globalz/__init__.py
globalz-0.1.0.dist-info/LICENSE
globalz-0.1.0.dist-info/WHEEL
globalz-0.1.0.dist-info/METADATA
globalz-0.1.0.dist-info/RECORD
