Metadata-Version: 2.1
Name: globalz
Version: 0.1.0
Summary: "I provide zee globalz\!" said the library in a thick French accent. "It's like Lua's _G object, but for Python\!"
Home-page: https://github.com/shawwn/globalz
License: MIT
Author: Shawn Presser
Requires-Python: >=3.6,<4.0
Classifier: License :: OSI Approved :: MIT License
Classifier: Programming Language :: Python :: 3
Classifier: Programming Language :: Python :: 3.6
Classifier: Programming Language :: Python :: 3.7
Classifier: Programming Language :: Python :: 3.8
Classifier: Programming Language :: Python :: 3.9
Project-URL: @theshawwn on Twitter, https://www.twitter.com/theshawwn
Project-URL: Shawn's Website, https://www.shawwn.com
Project-URL: Support me on Patreon, https://www.patreon.com/shawwn
Project-URL: sillysaurusx on Hacker News, https://news.ycombinator.com/threads?id=sillysaurusx
